circleci_env_cli.py
circleci_env_cli-0.2.2.dist-info/LICENSE
circleci_env_cli-0.2.2.dist-info/METADATA
circleci_env_cli-0.2.2.dist-info/WHEEL
circleci_env_cli-0.2.2.dist-info/entry_points.txt
circleci_env_cli-0.2.2.dist-info/top_level.txt
circleci_env_cli-0.2.2.dist-info/RECORD
