Metadata-Version: 2.1
Name: circleci-env-cli
Version: 0.2.2
Summary: CLI tool for manage CircleCI contexts and environment vars
Home-page: https://github.com/phsmith/circleci-env-cli
Author: Phillipe Smith
Author-email: phsmithcc@gmail.com
License: MIT
Keywords: circleci cli api
Platform: UNKNOWN
Classifier: Programming Language :: Python :: 3.10
Classifier: Operating System :: OS Independent
Requires-Python: >=3.7
License-File: LICENSE
Requires-Dist: click (==8.1.3)
Requires-Dist: pycircleci (==0.6.0)
Requires-Dist: requests (==2.28.2)
